scrapli_community/__init__.py
scrapli_community/py.typed
scrapli_community/aethra/__init__.py
scrapli_community/aethra/atosnt/__init__.py
scrapli_community/aethra/atosnt/aethra_atosnt.py
scrapli_community/aethra/atosnt/async_diver.py
scrapli_community/aethra/atosnt/sync_driver.py
scrapli_community/alcatel/__init__.py
scrapli_community/alcatel/aos/__init__.py
scrapli_community/alcatel/aos/alcatel_aos.py
scrapli_community/alcatel/aos/async_driver.py
scrapli_community/alcatel/aos/sync_driver.py
scrapli_community/aruba/__init__.py
scrapli_community/aruba/aoscx/__init__.py
scrapli_community/aruba/aoscx/aruba_aoscx.py
scrapli_community/aruba/aoscx/async_driver.py
scrapli_community/aruba/aoscx/sync_driver.py
scrapli_community/cisco/__init__.py
scrapli_community/cisco/aireos/__init__.py
scrapli_community/cisco/aireos/async_driver.py
scrapli_community/cisco/aireos/cisco_aireos.py
scrapli_community/cisco/aireos/sync_driver.py
scrapli_community/cisco/asa/__init__.py
scrapli_community/cisco/asa/async_driver.py
scrapli_community/cisco/asa/cisco_asa.py
scrapli_community/cisco/asa/sync_driver.py
scrapli_community/cisco/cbs/__init__.py
scrapli_community/cisco/cbs/async_driver.py
scrapli_community/cisco/cbs/cisco_cbs.py
scrapli_community/cisco/cbs/sync_driver.py
scrapli_community/cumulus/__init__.py
scrapli_community/cumulus/linux/__init__.py
scrapli_community/cumulus/linux/async_driver.py
scrapli_community/cumulus/linux/cumulus_linux.py
scrapli_community/cumulus/linux/sync_driver.py
scrapli_community/cumulus/vtysh/__init__.py
scrapli_community/cumulus/vtysh/async_driver.py
scrapli_community/cumulus/vtysh/cumulus_vtysh.py
scrapli_community/cumulus/vtysh/sync_driver.py
scrapli_community/datacom/__init__.py
scrapli_community/datacom/dmos/__init__.py
scrapli_community/datacom/dmos/async_driver.py
scrapli_community/datacom/dmos/datacom_dmos.py
scrapli_community/datacom/dmos/sync_driver.py
scrapli_community/datacom/dmswitch/__init__.py
scrapli_community/datacom/dmswitch/async_driver.py
scrapli_community-2024.7.30.dist-info/LICENSE
scrapli_community-2024.7.30.dist-info/METADATA
scrapli_community-2024.7.30.dist-info/WHEEL
scrapli_community-2024.7.30.dist-info/top_level.txt
scrapli_community-2024.7.30.dist-info/RECORD
