Metadata-Version: 2.1
Name: scrapli_community
Version: 2024.7.30
Summary: Easily add support for 'non-core' platforms to scrapli
Author-email: Carl Montanari <carl.r.montanari@gmail.com>
License: MIT License
Project-URL: Changelog, https://scrapli.github.io/scrapli_community/changelog/
Project-URL: Docs, https://scrapli.github.io/scrapli_community/
Project-URL: Homepage, https://github.com/scrapli/scrapli_community
Keywords: arista,automation,cisco,eos,iosxe,iosxr,juniper,junos,netconf,network,nxos,ssh,telnet
Classifier: License :: OSI Approved :: MIT License
Classifier: Operating System :: POSIX :: Linux
Classifier: Operating System :: MacOS
Classifier: Programming Language :: Python
Classifier: Programming Language :: Python :: 3.8
Classifier: Programming Language :: Python :: 3.9
Classifier: Programming Language :: Python :: 3.10
Classifier: Programming Language :: Python :: 3.11
Classifier: Programming Language :: Python :: 3.12
Classifier: Programming Language :: Python :: 3 :: Only
Classifier: Topic :: Software Development :: Libraries :: Python Modules
Requires-Python: >=3.8
License-File: LICENSE
Requires-Dist: scrapli>=2021.07.30a1
Provides-Extra: dev-darwin
Requires-Dist: black<25.0.0,>=23.3.0; extra == "dev-darwin"
Requires-Dist: darglint<2.0.0,>=1.8.1; extra == "dev-darwin"
Requires-Dist: isort<6.0.0,>=5.10.1; extra == "dev-darwin"
Requires-Dist: mypy<2.0.0,>=1.4.1; extra == "dev-darwin"
Requires-Dist: nox==2024.4.15; extra == "dev-darwin"
Requires-Dist: pycodestyle<3.0.0,>=2.8.0; extra == "dev-darwin"
Requires-Dist: pydocstyle<7.0.0,>=6.1.1; extra == "dev-darwin"
Requires-Dist: pylama<9.0.0,>=8.4.0; extra == "dev-darwin"
Requires-Dist: pylint<4.0.0,>=3.0.0; extra == "dev-darwin"
Requires-Dist: pytest-cov<5.0.0,>=3.0.0; extra == "dev-darwin"
Requires-Dist: pytest<8.0.0,>=7.0.0; extra == "dev-darwin"
Requires-Dist: toml<1.0.0,>=0.10.2; extra == "dev-darwin"
Provides-Extra: dev
Requires-Dist: black<25.0.0,>=23.3.0; extra == "dev"
Requires-Dist: darglint<2.0.0,>=1.8.1; extra == "dev"
Requires-Dist: isort<6.0.0,>=5.10.1; extra == "dev"
Requires-Dist: mypy<2.0.0,>=1.4.1; extra == "dev"
Requires-Dist: nox==2024.4.15; extra == "dev"
Requires-Dist: pycodestyle<3.0.0,>=2.8.0; extra == "dev"
Requires-Dist: pydocstyle<7.0.0,>=6.1.1; extra == "dev"
Requires-Dist: pylama<9.0.0,>=8.4.0; extra == "dev"
Requires-Dist: pylint<4.0.0,>=3.0.0; extra == "dev"
Requires-Dist: pytest-cov<5.0.0,>=3.0.0; extra == "dev"
Requires-Dist: pytest<8.0.0,>=7.0.0; extra == "dev"
Requires-Dist: toml<1.0.0,>=0.10.2; extra == "dev"
Provides-Extra: docs
Requires-Dist: mdx-gh-links<1.0,>=0.2; extra == "docs"
Requires-Dist: mkdocs<2.0.0,>=1.2.3; extra == "docs"
Requires-Dist: mkdocs-gen-files<1.0.0,>=0.4.0; extra == "docs"
Requires-Dist: mkdocs-literate-nav<1.0.0,>=0.5.0; extra == "docs"
Requires-Dist: mkdocs-material<10.0.0,>=8.1.6; extra == "docs"
Requires-Dist: mkdocs-material-extensions<2.0.0,>=1.0.3; extra == "docs"
Requires-Dist: mkdocs-section-index<1.0.0,>=0.3.4; extra == "docs"
Requires-Dist: mkdocstrings[python]<1.0.0,>=0.19.0; extra == "docs"
